src/__init__.py
src/action.py
src/code.py
src/file.py
src/instruct.py
src/reason.py
src/research.py
src/version.py
src/common/__init__.py
src/common/models.py
src/common/snippet.py
src/common/source.py
src/utils/__init__.py
src/utils/breakdown_pydantic.py
src/utils/create_path.py
src/utils/current_timestamp.py
src/utils/extract_json.py
src/utils/fuzzy_parse_json.py
src/utils/hash_dict.py
src/utils/parse_xml.py
src/utils/to_dict.py
src/utils/to_list.py
src/utils/to_num.py
lion_fields-0.1.0.dist-info/METADATA
lion_fields-0.1.0.dist-info/WHEEL
lion_fields-0.1.0.dist-info/licenses/LICENSE
lion_fields-0.1.0.dist-info/RECORD
